CHANGELOG.md
LICENCE.txt
MANIFEST.in
README.md
setup.py
gitrex/__init__.py
gitrex.egg-info/PKG-INFO
gitrex.egg-info/SOURCES.txt
gitrex.egg-info/dependency_links.txt
gitrex.egg-info/requires.txt
gitrex.egg-info/top_level.txt